bangla_keyword_extractor/__init__.py
bangla_keyword_extractor/custom_rake.py
bangla_keyword_extractor/keyword_extractor.py
bangla_keyword_extractor/data/stopwords.txt
bangla_keyword_extractor-0.0.18.dist-info/METADATA
bangla_keyword_extractor-0.0.18.dist-info/WHEEL
bangla_keyword_extractor-0.0.18.dist-info/RECORD
