Metadata-Version: 2.3
Name: bangla_keyword_extractor
Version: 0.0.18
Summary: Bangla keyword extraction library which extracts keywords from text or list of texts
Project-URL: Homepage, https://github.com/PolygonTechnology-xyz/bangla-keyword-extractor
Project-URL: Issues, https://github.com/PolygonTechnology-xyz/bangla-keyword-extractor/issues
Author-email: Kabin Hasan <kanchon@polygontech.xyz>
Classifier: License :: OSI Approved :: MIT License
Classifier: Operating System :: OS Independent
Classifier: Programming Language :: Python :: 3
Requires-Python: >=3.6
Requires-Dist: rake-nltk==1.0.6
Requires-Dist: tqdm==4.66.4
